<?xml version="1.0" encoding="utf-8"?>
<!DOCTYPE hibernate-mapping PUBLIC "-//Hibernate/Hibernate Mapping DTD 3.0//EN"
"http://hibernate.sourceforge.net/hibernate-mapping-3.0.dtd">
<!-- 
    Mapping file autogenerated by MyEclipse Persistence Tools
-->
<hibernate-mapping>
    <class name="com.in.entity.EmailAtta" table="EmailAtta" schema="dbo" catalog="oaManSystem">
        <id name="attaId" type="java.lang.Integer">
            <column name="atta_id" />
            <generator class="native"></generator>
        </id>
        <many-to-one name="email" class="com.in.entity.Email" fetch="select">
            <column name="atta_emailid" not-null="true" />
        </many-to-one>
        <property name="attaFilename" type="java.lang.String">
            <column name="atta_filename" />
        </property>
        <property name="attaFoldername" type="java.lang.String">
            <column name="atta_foldername" />
        </property>
    </class>
</hibernate-mapping>
